gst/__init__.py
gst/__main__.py
gst/class_error.py
gst/gst_utilities.py
effcorp_gst-1.7.1.dist-info/LICENSE
effcorp_gst-1.7.1.dist-info/METADATA
effcorp_gst-1.7.1.dist-info/WHEEL
effcorp_gst-1.7.1.dist-info/entry_points.txt
effcorp_gst-1.7.1.dist-info/top_level.txt
effcorp_gst-1.7.1.dist-info/RECORD
