Metadata-Version: 2.1
Name: effcorp-gst
Version: 1.7.1
Summary: A python module to simlify multiple GST related tasks in your day to day office work
Home-page: https://github.com/EFFICIENTCORPORATES/efffcorp-gst
Author: Efficient_Corporates
Author-email: efficientcorporates.info@gmail.com
License: GNU GP License
Platform: UNKNOWN
Classifier: License :: OSI Approved :: GNU General Public License v3 or later (GPLv3+)
Classifier: Programming Language :: Python :: 3.6
Classifier: Programming Language :: Python :: 3.7
Classifier: Programming Language :: Python :: 3.8
License-File: LICENSE
Requires-Dist: pandas
Requires-Dist: numpy
Requires-Dist: openpyxl
Requires-Dist: XlsxWriter
Requires-Dist: UliPlot
